telebaka_faq/__init__.py
telebaka_faq/admin.py
telebaka_faq/bot.py
telebaka_faq/models.py
telebaka_faq/migrations/0001_initial.py
telebaka_faq/migrations/0002_auto_20180915_1423.py
telebaka_faq/migrations/0003_auto_20180915_1436.py
telebaka_faq/migrations/__init__.py
telebaka_faq-0.1.12.dist-info/METADATA
telebaka_faq-0.1.12.dist-info/WHEEL
telebaka_faq-0.1.12.dist-info/top_level.txt
telebaka_faq-0.1.12.dist-info/RECORD
