Metadata-Version: 2.1
Name: telebaka-faq
Version: 0.1.12
Summary: UNKNOWN
Home-page: UNKNOWN
Author: bakatrouble
Author-email: bakatrouble@gmail.com
License: UNKNOWN
Platform: UNKNOWN
Requires-Dist: django
Requires-Dist: python-telegram-bot
Requires-Dist: telebakacore
Requires-Dist: django-admin-sortable2
